tbase_post/__init__.py
tbase_post/admin.py
tbase_post/apps.py
tbase_post/models.py
tbase_post/tests.py
tbase_post/urls.py
tbase_post/views.py
tbase_post/views.py:Zone.Identifier
tbase_post/migrations/__init__.py
tbase_post/migrations/__pycache__/0001_initial.cpython-310.pyc
tbase_post/migrations/__pycache__/0002_auto_20230421_1307.cpython-310.pyc
tbase_post/migrations/__pycache__/__init__.cpython-310.pyc
tbase_post/static/images/photo-1578707399887-e6d183c9e598.jpeg
tbase_post/static/images/photo-1578707399887-e6d183c9e598.jpeg:Zone.Identifier
tbase_post/templates/post/article_list_by_tag.html
tbase_post/templates/post/blog_index.html
tbase_post/templates/post/detail.html
tbase_post/templates/post/extras/related_post_by_tags.html
tbase_post/templates/post/extras/related_post_by_tags.html:Zone.Identifier
tbase_post/templates/post/extras/tags.html
tbase_post/templates/post/extras/tags.html:Zone.Identifier
tbase_post/templatetags/__init__.py
tbase_post/templatetags/__init__.py:Zone.Identifier
tbase_post/templatetags/post_extras.py
tbase_post/templatetags/post_extras.py:Zone.Identifier
tbase_post/templatetags/__pycache__/__init__.cpython-310.pyc
tbase_post/templatetags/__pycache__/post_extras.cpython-310.pyc
django_tbase_post-2023.5.2716851344.dist-info/METADATA
django_tbase_post-2023.5.2716851344.dist-info/WHEEL
django_tbase_post-2023.5.2716851344.dist-info/top_level.txt
django_tbase_post-2023.5.2716851344.dist-info/RECORD
